{
  "id": "f0ef83ef-0d7e-43bb-8a66-29a69b30da79",
  "prevId": "a2bafe20-b1b2-4bf6-aa93-5f0ac6c4601f",
  "version": "7",
  "dialect": "postgresql",
  "tables": {
    "public.dock_appointments": {
      "name": "dock_appointments",
      "schema": "",
      "columns": {
        "id": {
          "name": "id",
          "type": "uuid",
          "primaryKey": true,
          "notNull": true,
          "default": "gen_random_uuid()"
        },
        "org_id": {
          "name": "org_id",
          "type": "text",
          "primaryKey": false,
          "notNull": true
        },
        "warehouse_id": {
          "name": "warehouse_id",
          "type": "uuid",
          "primaryKey": false,
          "notNull": true
        },
        "dock_id": {
          "name": "dock_id",
          "type": "uuid",
          "primaryKey": false,
          "notNull": true
        },
        "vehicle_id": {
          "name": "vehicle_id",
          "type": "uuid",
          "primaryKey": false,
          "notNull": false
        },
        "direction": {
          "name": "direction",
          "type": "dock_direction",
          "typeSchema": "public",
          "primaryKey": false,
          "notNull": true
        },
        "pallet_count": {
          "name": "pallet_count",
          "type": "integer",
          "primaryKey": false,
          "notNull": false
        },
        "scheduled_start": {
          "name": "scheduled_start",
          "type": "timestamp with time zone",
          "primaryKey": false,
          "notNull": true
        },
        "scheduled_end": {
          "name": "scheduled_end",
          "type": "timestamp with time zone",
          "primaryKey": false,
          "notNull": true
        },
        "actual_start": {
          "name": "actual_start",
          "type": "timestamp with time zone",
          "primaryKey": false,
          "notNull": false
        },
        "actual_end": {
          "name": "actual_end",
          "type": "timestamp with time zone",
          "primaryKey": false,
          "notNull": false
        },
        "status": {
          "name": "status",
          "type": "dock_appointment_status",
          "typeSchema": "public",
          "primaryKey": false,
          "notNull": true,
          "default": "'scheduled'"
        },
        "processing_notes": {
          "name": "processing_notes",
          "type": "text",
          "primaryKey": false,
          "notNull": false
        },
        "created_at": {
          "name": "created_at",
          "type": "timestamp with time zone",
          "primaryKey": false,
          "notNull": true,
          "default": "now()"
        },
        "updated_at": {
          "name": "updated_at",
          "type": "timestamp with time zone",
          "primaryKey": false,
          "notNull": true,
          "default": "now()"
        }
      },
      "indexes": {
        "dock_appointments_org_id_idx": {
          "name": "dock_appointments_org_id_idx",
          "columns": [
            {
              "expression": "org_id",
              "isExpression": false,
              "asc": true,
              "nulls": "last"
            }
          ],
          "isUnique": false,
          "concurrently": false,
          "method": "btree",
          "with": {}
        },
        "dock_appointments_warehouse_id_idx": {
          "name": "dock_appointments_warehouse_id_idx",
          "columns": [
            {
              "expression": "warehouse_id",
              "isExpression": false,
              "asc": true,
              "nulls": "last"
            }
          ],
          "isUnique": false,
          "concurrently": false,
          "method": "btree",
          "with": {}
        },
        "dock_appointments_dock_id_idx": {
          "name": "dock_appointments_dock_id_idx",
          "columns": [
            {
              "expression": "dock_id",
              "isExpression": false,
              "asc": true,
              "nulls": "last"
            }
          ],
          "isUnique": false,
          "concurrently": false,
          "method": "btree",
          "with": {}
        },
        "dock_appointments_scheduled_start_idx": {
          "name": "dock_appointments_scheduled_start_idx",
          "columns": [
            {
              "expression": "scheduled_start",
              "isExpression": false,
              "asc": true,
              "nulls": "last"
            }
          ],
          "isUnique": false,
          "concurrently": false,
          "method": "btree",
          "with": {}
        }
      },
      "foreignKeys": {
        "dock_appointments_warehouse_id_warehouses_id_fk": {
          "name": "dock_appointments_warehouse_id_warehouses_id_fk",
          "tableFrom": "dock_appointments",
          "tableTo": "warehouses",
          "columnsFrom": [
            "warehouse_id"
          ],
          "columnsTo": [
            "id"
          ],
          "onDelete": "cascade",
          "onUpdate": "no action"
        },
        "dock_appointments_dock_id_docks_id_fk": {
          "name": "dock_appointments_dock_id_docks_id_fk",
          "tableFrom": "dock_appointments",
          "tableTo": "docks",
          "columnsFrom": [
            "dock_id"
          ],
          "columnsTo": [
            "id"
          ],
          "onDelete": "cascade",
          "onUpdate": "no action"
        }
      },
      "compositePrimaryKeys": {},
      "uniqueConstraints": {},
      "policies": {},
      "checkConstraints": {},
      "isRLSEnabled": false
    },
    "public.docks": {
      "name": "docks",
      "schema": "",
      "columns": {
        "id": {
          "name": "id",
          "type": "uuid",
          "primaryKey": true,
          "notNull": true,
          "default": "gen_random_uuid()"
        },
        "org_id": {
          "name": "org_id",
          "type": "text",
          "primaryKey": false,
          "notNull": true
        },
        "warehouse_id": {
          "name": "warehouse_id",
          "type": "uuid",
          "primaryKey": false,
          "notNull": true
        },
        "code": {
          "name": "code",
          "type": "text",
          "primaryKey": false,
          "notNull": true
        },
        "direction": {
          "name": "direction",
          "type": "dock_direction",
          "typeSchema": "public",
          "primaryKey": false,
          "notNull": true,
          "default": "'both'"
        },
        "created_at": {
          "name": "created_at",
          "type": "timestamp with time zone",
          "primaryKey": false,
          "notNull": true,
          "default": "now()"
        },
        "updated_at": {
          "name": "updated_at",
          "type": "timestamp with time zone",
          "primaryKey": false,
          "notNull": true,
          "default": "now()"
        }
      },
      "indexes": {
        "docks_org_id_idx": {
          "name": "docks_org_id_idx",
          "columns": [
            {
              "expression": "org_id",
              "isExpression": false,
              "asc": true,
              "nulls": "last"
            }
          ],
          "isUnique": false,
          "concurrently": false,
          "method": "btree",
          "with": {}
        },
        "docks_warehouse_id_idx": {
          "name": "docks_warehouse_id_idx",
          "columns": [
            {
              "expression": "warehouse_id",
              "isExpression": false,
              "asc": true,
              "nulls": "last"
            }
          ],
          "isUnique": false,
          "concurrently": false,
          "method": "btree",
          "with": {}
        },
        "docks_warehouse_code_idx": {
          "name": "docks_warehouse_code_idx",
          "columns": [
            {
              "expression": "warehouse_id",
              "isExpression": false,
              "asc": true,
              "nulls": "last"
            },
            {
              "expression": "code",
              "isExpression": false,
              "asc": true,
              "nulls": "last"
            }
          ],
          "isUnique": true,
          "concurrently": false,
          "method": "btree",
          "with": {}
        }
      },
      "foreignKeys": {
        "docks_warehouse_id_warehouses_id_fk": {
          "name": "docks_warehouse_id_warehouses_id_fk",
          "tableFrom": "docks",
          "tableTo": "warehouses",
          "columnsFrom": [
            "warehouse_id"
          ],
          "columnsTo": [
            "id"
          ],
          "onDelete": "cascade",
          "onUpdate": "no action"
        }
      },
      "compositePrimaryKeys": {},
      "uniqueConstraints": {},
      "policies": {},
      "checkConstraints": {},
      "isRLSEnabled": false
    },
    "public.forklift_configs": {
      "name": "forklift_configs",
      "schema": "",
      "columns": {
        "id": {
          "name": "id",
          "type": "uuid",
          "primaryKey": true,
          "notNull": true,
          "default": "gen_random_uuid()"
        },
        "org_id": {
          "name": "org_id",
          "type": "text",
          "primaryKey": false,
          "notNull": true
        },
        "warehouse_id": {
          "name": "warehouse_id",
          "type": "uuid",
          "primaryKey": false,
          "notNull": true
        },
        "qty": {
          "name": "qty",
          "type": "integer",
          "primaryKey": false,
          "notNull": true,
          "default": 1
        },
        "avg_minutes_per_pallet": {
          "name": "avg_minutes_per_pallet",
          "type": "real",
          "primaryKey": false,
          "notNull": true,
          "default": 5
        },
        "created_at": {
          "name": "created_at",
          "type": "timestamp with time zone",
          "primaryKey": false,
          "notNull": true,
          "default": "now()"
        },
        "updated_at": {
          "name": "updated_at",
          "type": "timestamp with time zone",
          "primaryKey": false,
          "notNull": true,
          "default": "now()"
        }
      },
      "indexes": {},
      "foreignKeys": {
        "forklift_configs_warehouse_id_warehouses_id_fk": {
          "name": "forklift_configs_warehouse_id_warehouses_id_fk",
          "tableFrom": "forklift_configs",
          "tableTo": "warehouses",
          "columnsFrom": [
            "warehouse_id"
          ],
          "columnsTo": [
            "id"
          ],
          "onDelete": "cascade",
          "onUpdate": "no action"
        }
      },
      "compositePrimaryKeys": {},
      "uniqueConstraints": {},
      "policies": {},
      "checkConstraints": {},
      "isRLSEnabled": false
    },
    "public.locations": {
      "name": "locations",
      "schema": "",
      "columns": {
        "id": {
          "name": "id",
          "type": "uuid",
          "primaryKey": true,
          "notNull": true,
          "default": "gen_random_uuid()"
        },
        "org_id": {
          "name": "org_id",
          "type": "text",
          "primaryKey": false,
          "notNull": true
        },
        "warehouse_id": {
          "name": "warehouse_id",
          "type": "uuid",
          "primaryKey": false,
          "notNull": true
        },
        "zone_id": {
          "name": "zone_id",
          "type": "uuid",
          "primaryKey": false,
          "notNull": false
        },
        "code": {
          "name": "code",
          "type": "text",
          "primaryKey": false,
          "notNull": true
        },
        "type": {
          "name": "type",
          "type": "location_type",
          "typeSchema": "public",
          "primaryKey": false,
          "notNull": true,
          "default": "'rack'"
        },
        "level": {
          "name": "level",
          "type": "integer",
          "primaryKey": false,
          "notNull": false
        },
        "capacity_volume": {
          "name": "capacity_volume",
          "type": "double precision",
          "primaryKey": false,
          "notNull": false
        },
        "capacity_weight": {
          "name": "capacity_weight",
          "type": "double precision",
          "primaryKey": false,
          "notNull": false
        },
        "distance_to_dock": {
          "name": "distance_to_dock",
          "type": "double precision",
          "primaryKey": false,
          "notNull": false
        },
        "pos_x": {
          "name": "pos_x",
          "type": "integer",
          "primaryKey": false,
          "notNull": false
        },
        "pos_y": {
          "name": "pos_y",
          "type": "integer",
          "primaryKey": false,
          "notNull": false
        },
        "pos_width": {
          "name": "pos_width",
          "type": "integer",
          "primaryKey": false,
          "notNull": false
        },
        "pos_height": {
          "name": "pos_height",
          "type": "integer",
          "primaryKey": false,
          "notNull": false
        },
        "created_at": {
          "name": "created_at",
          "type": "timestamp with time zone",
          "primaryKey": false,
          "notNull": true,
          "default": "now()"
        },
        "updated_at": {
          "name": "updated_at",
          "type": "timestamp with time zone",
          "primaryKey": false,
          "notNull": true,
          "default": "now()"
        }
      },
      "indexes": {
        "locations_org_id_idx": {
          "name": "locations_org_id_idx",
          "columns": [
            {
              "expression": "org_id",
              "isExpression": false,
              "asc": true,
              "nulls": "last"
            }
          ],
          "isUnique": false,
          "concurrently": false,
          "method": "btree",
          "with": {}
        },
        "locations_warehouse_id_idx": {
          "name": "locations_warehouse_id_idx",
          "columns": [
            {
              "expression": "warehouse_id",
              "isExpression": false,
              "asc": true,
              "nulls": "last"
            }
          ],
          "isUnique": false,
          "concurrently": false,
          "method": "btree",
          "with": {}
        },
        "locations_zone_id_idx": {
          "name": "locations_zone_id_idx",
          "columns": [
            {
              "expression": "zone_id",
              "isExpression": false,
              "asc": true,
              "nulls": "last"
            }
          ],
          "isUnique": false,
          "concurrently": false,
          "method": "btree",
          "with": {}
        },
        "locations_warehouse_code_idx": {
          "name": "locations_warehouse_code_idx",
          "columns": [
            {
              "expression": "warehouse_id",
              "isExpression": false,
              "asc": true,
              "nulls": "last"
            },
            {
              "expression": "code",
              "isExpression": false,
              "asc": true,
              "nulls": "last"
            }
          ],
          "isUnique": true,
          "concurrently": false,
          "method": "btree",
          "with": {}
        }
      },
      "foreignKeys": {
        "locations_warehouse_id_warehouses_id_fk": {
          "name": "locations_warehouse_id_warehouses_id_fk",
          "tableFrom": "locations",
          "tableTo": "warehouses",
          "columnsFrom": [
            "warehouse_id"
          ],
          "columnsTo": [
            "id"
          ],
          "onDelete": "cascade",
          "onUpdate": "no action"
        },
        "locations_zone_id_zones_id_fk": {
          "name": "locations_zone_id_zones_id_fk",
          "tableFrom": "locations",
          "tableTo": "zones",
          "columnsFrom": [
            "zone_id"
          ],
          "columnsTo": [
            "id"
          ],
          "onDelete": "set null",
          "onUpdate": "no action"
        }
      },
      "compositePrimaryKeys": {},
      "uniqueConstraints": {},
      "policies": {},
      "checkConstraints": {},
      "isRLSEnabled": false
    },
    "public.slotting_runs": {
      "name": "slotting_runs",
      "schema": "",
      "columns": {
        "id": {
          "name": "id",
          "type": "uuid",
          "primaryKey": true,
          "notNull": true,
          "default": "gen_random_uuid()"
        },
        "org_id": {
          "name": "org_id",
          "type": "text",
          "primaryKey": false,
          "notNull": true
        },
        "warehouse_id": {
          "name": "warehouse_id",
          "type": "uuid",
          "primaryKey": false,
          "notNull": true
        },
        "run_at": {
          "name": "run_at",
          "type": "timestamp with time zone",
          "primaryKey": false,
          "notNull": true,
          "default": "now()"
        },
        "moved_count": {
          "name": "moved_count",
          "type": "integer",
          "primaryKey": false,
          "notNull": true,
          "default": 0
        },
        "recommendations": {
          "name": "recommendations",
          "type": "jsonb",
          "primaryKey": false,
          "notNull": true,
          "default": "'[]'::jsonb"
        },
        "created_at": {
          "name": "created_at",
          "type": "timestamp with time zone",
          "primaryKey": false,
          "notNull": true,
          "default": "now()"
        },
        "updated_at": {
          "name": "updated_at",
          "type": "timestamp with time zone",
          "primaryKey": false,
          "notNull": true,
          "default": "now()"
        }
      },
      "indexes": {
        "slotting_runs_org_id_idx": {
          "name": "slotting_runs_org_id_idx",
          "columns": [
            {
              "expression": "org_id",
              "isExpression": false,
              "asc": true,
              "nulls": "last"
            }
          ],
          "isUnique": false,
          "concurrently": false,
          "method": "btree",
          "with": {}
        },
        "slotting_runs_warehouse_id_idx": {
          "name": "slotting_runs_warehouse_id_idx",
          "columns": [
            {
              "expression": "warehouse_id",
              "isExpression": false,
              "asc": true,
              "nulls": "last"
            }
          ],
          "isUnique": false,
          "concurrently": false,
          "method": "btree",
          "with": {}
        },
        "slotting_runs_run_at_idx": {
          "name": "slotting_runs_run_at_idx",
          "columns": [
            {
              "expression": "run_at",
              "isExpression": false,
              "asc": true,
              "nulls": "last"
            }
          ],
          "isUnique": false,
          "concurrently": false,
          "method": "btree",
          "with": {}
        }
      },
      "foreignKeys": {
        "slotting_runs_warehouse_id_warehouses_id_fk": {
          "name": "slotting_runs_warehouse_id_warehouses_id_fk",
          "tableFrom": "slotting_runs",
          "tableTo": "warehouses",
          "columnsFrom": [
            "warehouse_id"
          ],
          "columnsTo": [
            "id"
          ],
          "onDelete": "cascade",
          "onUpdate": "no action"
        }
      },
      "compositePrimaryKeys": {},
      "uniqueConstraints": {},
      "policies": {},
      "checkConstraints": {},
      "isRLSEnabled": false
    },
    "public.warehouses": {
      "name": "warehouses",
      "schema": "",
      "columns": {
        "id": {
          "name": "id",
          "type": "uuid",
          "primaryKey": true,
          "notNull": true,
          "default": "gen_random_uuid()"
        },
        "org_id": {
          "name": "org_id",
          "type": "text",
          "primaryKey": false,
          "notNull": true
        },
        "name": {
          "name": "name",
          "type": "text",
          "primaryKey": false,
          "notNull": true
        },
        "code": {
          "name": "code",
          "type": "text",
          "primaryKey": false,
          "notNull": true
        },
        "address": {
          "name": "address",
          "type": "text",
          "primaryKey": false,
          "notNull": false
        },
        "lat": {
          "name": "lat",
          "type": "double precision",
          "primaryKey": false,
          "notNull": false
        },
        "lng": {
          "name": "lng",
          "type": "double precision",
          "primaryKey": false,
          "notNull": false
        },
        "created_at": {
          "name": "created_at",
          "type": "timestamp with time zone",
          "primaryKey": false,
          "notNull": true,
          "default": "now()"
        },
        "updated_at": {
          "name": "updated_at",
          "type": "timestamp with time zone",
          "primaryKey": false,
          "notNull": true,
          "default": "now()"
        }
      },
      "indexes": {
        "warehouses_org_id_idx": {
          "name": "warehouses_org_id_idx",
          "columns": [
            {
              "expression": "org_id",
              "isExpression": false,
              "asc": true,
              "nulls": "last"
            }
          ],
          "isUnique": false,
          "concurrently": false,
          "method": "btree",
          "with": {}
        },
        "warehouses_org_code_idx": {
          "name": "warehouses_org_code_idx",
          "columns": [
            {
              "expression": "org_id",
              "isExpression": false,
              "asc": true,
              "nulls": "last"
            },
            {
              "expression": "code",
              "isExpression": false,
              "asc": true,
              "nulls": "last"
            }
          ],
          "isUnique": true,
          "concurrently": false,
          "method": "btree",
          "with": {}
        }
      },
      "foreignKeys": {},
      "compositePrimaryKeys": {},
      "uniqueConstraints": {},
      "policies": {},
      "checkConstraints": {},
      "isRLSEnabled": false
    },
    "public.zones": {
      "name": "zones",
      "schema": "",
      "columns": {
        "id": {
          "name": "id",
          "type": "uuid",
          "primaryKey": true,
          "notNull": true,
          "default": "gen_random_uuid()"
        },
        "org_id": {
          "name": "org_id",
          "type": "text",
          "primaryKey": false,
          "notNull": true
        },
        "warehouse_id": {
          "name": "warehouse_id",
          "type": "uuid",
          "primaryKey": false,
          "notNull": true
        },
        "name": {
          "name": "name",
          "type": "text",
          "primaryKey": false,
          "notNull": true
        },
        "code": {
          "name": "code",
          "type": "text",
          "primaryKey": false,
          "notNull": true
        },
        "created_at": {
          "name": "created_at",
          "type": "timestamp with time zone",
          "primaryKey": false,
          "notNull": true,
          "default": "now()"
        },
        "updated_at": {
          "name": "updated_at",
          "type": "timestamp with time zone",
          "primaryKey": false,
          "notNull": true,
          "default": "now()"
        }
      },
      "indexes": {
        "zones_org_id_idx": {
          "name": "zones_org_id_idx",
          "columns": [
            {
              "expression": "org_id",
              "isExpression": false,
              "asc": true,
              "nulls": "last"
            }
          ],
          "isUnique": false,
          "concurrently": false,
          "method": "btree",
          "with": {}
        },
        "zones_warehouse_id_idx": {
          "name": "zones_warehouse_id_idx",
          "columns": [
            {
              "expression": "warehouse_id",
              "isExpression": false,
              "asc": true,
              "nulls": "last"
            }
          ],
          "isUnique": false,
          "concurrently": false,
          "method": "btree",
          "with": {}
        }
      },
      "foreignKeys": {
        "zones_warehouse_id_warehouses_id_fk": {
          "name": "zones_warehouse_id_warehouses_id_fk",
          "tableFrom": "zones",
          "tableTo": "warehouses",
          "columnsFrom": [
            "warehouse_id"
          ],
          "columnsTo": [
            "id"
          ],
          "onDelete": "cascade",
          "onUpdate": "no action"
        }
      },
      "compositePrimaryKeys": {},
      "uniqueConstraints": {},
      "policies": {},
      "checkConstraints": {},
      "isRLSEnabled": false
    },
    "public.employees": {
      "name": "employees",
      "schema": "",
      "columns": {
        "id": {
          "name": "id",
          "type": "uuid",
          "primaryKey": true,
          "notNull": true,
          "default": "gen_random_uuid()"
        },
        "org_id": {
          "name": "org_id",
          "type": "text",
          "primaryKey": false,
          "notNull": true
        },
        "warehouse_id": {
          "name": "warehouse_id",
          "type": "uuid",
          "primaryKey": false,
          "notNull": false
        },
        "full_name": {
          "name": "full_name",
          "type": "text",
          "primaryKey": false,
          "notNull": true
        },
        "role": {
          "name": "role",
          "type": "text",
          "primaryKey": false,
          "notNull": false
        },
        "department": {
          "name": "department",
          "type": "text",
          "primaryKey": false,
          "notNull": false
        },
        "hire_date": {
          "name": "hire_date",
          "type": "date",
          "primaryKey": false,
          "notNull": true
        },
        "termination_date": {
          "name": "termination_date",
          "type": "date",
          "primaryKey": false,
          "notNull": false
        },
        "status": {
          "name": "status",
          "type": "employee_status",
          "typeSchema": "public",
          "primaryKey": false,
          "notNull": true,
          "default": "'active'"
        },
        "created_at": {
          "name": "created_at",
          "type": "timestamp with time zone",
          "primaryKey": false,
          "notNull": true,
          "default": "now()"
        },
        "updated_at": {
          "name": "updated_at",
          "type": "timestamp with time zone",
          "primaryKey": false,
          "notNull": true,
          "default": "now()"
        }
      },
      "indexes": {
        "employees_org_id_idx": {
          "name": "employees_org_id_idx",
          "columns": [
            {
              "expression": "org_id",
              "isExpression": false,
              "asc": true,
              "nulls": "last"
            }
          ],
          "isUnique": false,
          "concurrently": false,
          "method": "btree",
          "with": {}
        },
        "employees_warehouse_id_idx": {
          "name": "employees_warehouse_id_idx",
          "columns": [
            {
              "expression": "warehouse_id",
              "isExpression": false,
              "asc": true,
              "nulls": "last"
            }
          ],
          "isUnique": false,
          "concurrently": false,
          "method": "btree",
          "with": {}
        },
        "employees_status_idx": {
          "name": "employees_status_idx",
          "columns": [
            {
              "expression": "status",
              "isExpression": false,
              "asc": true,
              "nulls": "last"
            }
          ],
          "isUnique": false,
          "concurrently": false,
          "method": "btree",
          "with": {}
        }
      },
      "foreignKeys": {
        "employees_warehouse_id_warehouses_id_fk": {
          "name": "employees_warehouse_id_warehouses_id_fk",
          "tableFrom": "employees",
          "tableTo": "warehouses",
          "columnsFrom": [
            "warehouse_id"
          ],
          "columnsTo": [
            "id"
          ],
          "onDelete": "set null",
          "onUpdate": "no action"
        }
      },
      "compositePrimaryKeys": {},
      "uniqueConstraints": {},
      "policies": {},
      "checkConstraints": {},
      "isRLSEnabled": false
    },
    "public.staffing_plans": {
      "name": "staffing_plans",
      "schema": "",
      "columns": {
        "id": {
          "name": "id",
          "type": "uuid",
          "primaryKey": true,
          "notNull": true,
          "default": "gen_random_uuid()"
        },
        "org_id": {
          "name": "org_id",
          "type": "text",
          "primaryKey": false,
          "notNull": true
        },
        "warehouse_id": {
          "name": "warehouse_id",
          "type": "uuid",
          "primaryKey": false,
          "notNull": false
        },
        "name": {
          "name": "name",
          "type": "text",
          "primaryKey": false,
          "notNull": true
        },
        "available_headcount": {
          "name": "available_headcount",
          "type": "integer",
          "primaryKey": false,
          "notNull": true,
          "default": 1
        },
        "status": {
          "name": "status",
          "type": "staffing_plan_status",
          "typeSchema": "public",
          "primaryKey": false,
          "notNull": true,
          "default": "'draft'"
        },
        "critical_path_hours": {
          "name": "critical_path_hours",
          "type": "real",
          "primaryKey": false,
          "notNull": false
        },
        "created_at": {
          "name": "created_at",
          "type": "timestamp with time zone",
          "primaryKey": false,
          "notNull": true,
          "default": "now()"
        },
        "updated_at": {
          "name": "updated_at",
          "type": "timestamp with time zone",
          "primaryKey": false,
          "notNull": true,
          "default": "now()"
        }
      },
      "indexes": {
        "staffing_plans_org_id_idx": {
          "name": "staffing_plans_org_id_idx",
          "columns": [
            {
              "expression": "org_id",
              "isExpression": false,
              "asc": true,
              "nulls": "last"
            }
          ],
          "isUnique": false,
          "concurrently": false,
          "method": "btree",
          "with": {}
        },
        "staffing_plans_warehouse_id_idx": {
          "name": "staffing_plans_warehouse_id_idx",
          "columns": [
            {
              "expression": "warehouse_id",
              "isExpression": false,
              "asc": true,
              "nulls": "last"
            }
          ],
          "isUnique": false,
          "concurrently": false,
          "method": "btree",
          "with": {}
        }
      },
      "foreignKeys": {
        "staffing_plans_warehouse_id_warehouses_id_fk": {
          "name": "staffing_plans_warehouse_id_warehouses_id_fk",
          "tableFrom": "staffing_plans",
          "tableTo": "warehouses",
          "columnsFrom": [
            "warehouse_id"
          ],
          "columnsTo": [
            "id"
          ],
          "onDelete": "set null",
          "onUpdate": "no action"
        }
      },
      "compositePrimaryKeys": {},
      "uniqueConstraints": {},
      "policies": {},
      "checkConstraints": {},
      "isRLSEnabled": false
    },
    "public.work_tasks": {
      "name": "work_tasks",
      "schema": "",
      "columns": {
        "id": {
          "name": "id",
          "type": "uuid",
          "primaryKey": true,
          "notNull": true,
          "default": "gen_random_uuid()"
        },
        "org_id": {
          "name": "org_id",
          "type": "text",
          "primaryKey": false,
          "notNull": true
        },
        "plan_id": {
          "name": "plan_id",
          "type": "uuid",
          "primaryKey": false,
          "notNull": true
        },
        "name": {
          "name": "name",
          "type": "text",
          "primaryKey": false,
          "notNull": true
        },
        "duration_hours": {
          "name": "duration_hours",
          "type": "real",
          "primaryKey": false,
          "notNull": true
        },
        "predecessor_ids": {
          "name": "predecessor_ids",
          "type": "jsonb",
          "primaryKey": false,
          "notNull": true,
          "default": "'[]'::jsonb"
        },
        "required_headcount": {
          "name": "required_headcount",
          "type": "integer",
          "primaryKey": false,
          "notNull": true,
          "default": 1
        },
        "assigned_employee_ids": {
          "name": "assigned_employee_ids",
          "type": "jsonb",
          "primaryKey": false,
          "notNull": true,
          "default": "'[]'::jsonb"
        },
        "early_start": {
          "name": "early_start",
          "type": "real",
          "primaryKey": false,
          "notNull": false
        },
        "early_finish": {
          "name": "early_finish",
          "type": "real",
          "primaryKey": false,
          "notNull": false
        },
        "late_start": {
          "name": "late_start",
          "type": "real",
          "primaryKey": false,
          "notNull": false
        },
        "late_finish": {
          "name": "late_finish",
          "type": "real",
          "primaryKey": false,
          "notNull": false
        },
        "total_float": {
          "name": "total_float",
          "type": "real",
          "primaryKey": false,
          "notNull": false
        },
        "is_critical": {
          "name": "is_critical",
          "type": "integer",
          "primaryKey": false,
          "notNull": true,
          "default": 0
        },
        "color": {
          "name": "color",
          "type": "text",
          "primaryKey": false,
          "notNull": false
        },
        "created_at": {
          "name": "created_at",
          "type": "timestamp with time zone",
          "primaryKey": false,
          "notNull": true,
          "default": "now()"
        },
        "updated_at": {
          "name": "updated_at",
          "type": "timestamp with time zone",
          "primaryKey": false,
          "notNull": true,
          "default": "now()"
        }
      },
      "indexes": {
        "work_tasks_org_id_idx": {
          "name": "work_tasks_org_id_idx",
          "columns": [
            {
              "expression": "org_id",
              "isExpression": false,
              "asc": true,
              "nulls": "last"
            }
          ],
          "isUnique": false,
          "concurrently": false,
          "method": "btree",
          "with": {}
        },
        "work_tasks_plan_id_idx": {
          "name": "work_tasks_plan_id_idx",
          "columns": [
            {
              "expression": "plan_id",
              "isExpression": false,
              "asc": true,
              "nulls": "last"
            }
          ],
          "isUnique": false,
          "concurrently": false,
          "method": "btree",
          "with": {}
        }
      },
      "foreignKeys": {
        "work_tasks_plan_id_staffing_plans_id_fk": {
          "name": "work_tasks_plan_id_staffing_plans_id_fk",
          "tableFrom": "work_tasks",
          "tableTo": "staffing_plans",
          "columnsFrom": [
            "plan_id"
          ],
          "columnsTo": [
            "id"
          ],
          "onDelete": "cascade",
          "onUpdate": "no action"
        }
      },
      "compositePrimaryKeys": {},
      "uniqueConstraints": {},
      "policies": {},
      "checkConstraints": {},
      "isRLSEnabled": false
    },
    "public.inventory_lots": {
      "name": "inventory_lots",
      "schema": "",
      "columns": {
        "id": {
          "name": "id",
          "type": "uuid",
          "primaryKey": true,
          "notNull": true,
          "default": "gen_random_uuid()"
        },
        "org_id": {
          "name": "org_id",
          "type": "text",
          "primaryKey": false,
          "notNull": true
        },
        "sku_id": {
          "name": "sku_id",
          "type": "uuid",
          "primaryKey": false,
          "notNull": true
        },
        "warehouse_id": {
          "name": "warehouse_id",
          "type": "uuid",
          "primaryKey": false,
          "notNull": true
        },
        "location_id": {
          "name": "location_id",
          "type": "uuid",
          "primaryKey": false,
          "notNull": false
        },
        "lot_no": {
          "name": "lot_no",
          "type": "text",
          "primaryKey": false,
          "notNull": true
        },
        "qty": {
          "name": "qty",
          "type": "double precision",
          "primaryKey": false,
          "notNull": true
        },
        "received_date": {
          "name": "received_date",
          "type": "date",
          "primaryKey": false,
          "notNull": true
        },
        "expiry_date": {
          "name": "expiry_date",
          "type": "date",
          "primaryKey": false,
          "notNull": false
        },
        "status": {
          "name": "status",
          "type": "inventory_lot_status",
          "typeSchema": "public",
          "primaryKey": false,
          "notNull": true,
          "default": "'available'"
        },
        "created_at": {
          "name": "created_at",
          "type": "timestamp with time zone",
          "primaryKey": false,
          "notNull": true,
          "default": "now()"
        },
        "updated_at": {
          "name": "updated_at",
          "type": "timestamp with time zone",
          "primaryKey": false,
          "notNull": true,
          "default": "now()"
        }
      },
      "indexes": {
        "inventory_lots_org_id_idx": {
          "name": "inventory_lots_org_id_idx",
          "columns": [
            {
              "expression": "org_id",
              "isExpression": false,
              "asc": true,
              "nulls": "last"
            }
          ],
          "isUnique": false,
          "concurrently": false,
          "method": "btree",
          "with": {}
        },
        "inventory_lots_sku_id_idx": {
          "name": "inventory_lots_sku_id_idx",
          "columns": [
            {
              "expression": "sku_id",
              "isExpression": false,
              "asc": true,
              "nulls": "last"
            }
          ],
          "isUnique": false,
          "concurrently": false,
          "method": "btree",
          "with": {}
        },
        "inventory_lots_warehouse_id_idx": {
          "name": "inventory_lots_warehouse_id_idx",
          "columns": [
            {
              "expression": "warehouse_id",
              "isExpression": false,
              "asc": true,
              "nulls": "last"
            }
          ],
          "isUnique": false,
          "concurrently": false,
          "method": "btree",
          "with": {}
        },
        "inventory_lots_location_id_idx": {
          "name": "inventory_lots_location_id_idx",
          "columns": [
            {
              "expression": "location_id",
              "isExpression": false,
              "asc": true,
              "nulls": "last"
            }
          ],
          "isUnique": false,
          "concurrently": false,
          "method": "btree",
          "with": {}
        },
        "inventory_lots_status_idx": {
          "name": "inventory_lots_status_idx",
          "columns": [
            {
              "expression": "status",
              "isExpression": false,
              "asc": true,
              "nulls": "last"
            }
          ],
          "isUnique": false,
          "concurrently": false,
          "method": "btree",
          "with": {}
        }
      },
      "foreignKeys": {
        "inventory_lots_sku_id_product_skus_id_fk": {
          "name": "inventory_lots_sku_id_product_skus_id_fk",
          "tableFrom": "inventory_lots",
          "tableTo": "product_skus",
          "columnsFrom": [
            "sku_id"
          ],
          "columnsTo": [
            "id"
          ],
          "onDelete": "restrict",
          "onUpdate": "no action"
        },
        "inventory_lots_warehouse_id_warehouses_id_fk": {
          "name": "inventory_lots_warehouse_id_warehouses_id_fk",
          "tableFrom": "inventory_lots",
          "tableTo": "warehouses",
          "columnsFrom": [
            "warehouse_id"
          ],
          "columnsTo": [
            "id"
          ],
          "onDelete": "restrict",
          "onUpdate": "no action"
        },
        "inventory_lots_location_id_locations_id_fk": {
          "name": "inventory_lots_location_id_locations_id_fk",
          "tableFrom": "inventory_lots",
          "tableTo": "locations",
          "columnsFrom": [
            "location_id"
          ],
          "columnsTo": [
            "id"
          ],
          "onDelete": "set null",
          "onUpdate": "no action"
        }
      },
      "compositePrimaryKeys": {},
      "uniqueConstraints": {},
      "policies": {},
      "checkConstraints": {},
      "isRLSEnabled": false
    },
    "public.inventory_transactions": {
      "name": "inventory_transactions",
      "schema": "",
      "columns": {
        "id": {
          "name": "id",
          "type": "uuid",
          "primaryKey": true,
          "notNull": true,
          "default": "gen_random_uuid()"
        },
        "org_id": {
          "name": "org_id",
          "type": "text",
          "primaryKey": false,
          "notNull": true
        },
        "warehouse_id": {
          "name": "warehouse_id",
          "type": "uuid",
          "primaryKey": false,
          "notNull": true
        },
        "type": {
          "name": "type",
          "type": "inventory_transaction_type",
          "typeSchema": "public",
          "primaryKey": false,
          "notNull": true
        },
        "sku_id": {
          "name": "sku_id",
          "type": "uuid",
          "primaryKey": false,
          "notNull": true
        },
        "lot_id": {
          "name": "lot_id",
          "type": "uuid",
          "primaryKey": false,
          "notNull": false
        },
        "qty": {
          "name": "qty",
          "type": "double precision",
          "primaryKey": false,
          "notNull": true
        },
        "from_location_id": {
          "name": "from_location_id",
          "type": "uuid",
          "primaryKey": false,
          "notNull": false
        },
        "to_location_id": {
          "name": "to_location_id",
          "type": "uuid",
          "primaryKey": false,
          "notNull": false
        },
        "performed_by": {
          "name": "performed_by",
          "type": "uuid",
          "primaryKey": false,
          "notNull": false
        },
        "note": {
          "name": "note",
          "type": "text",
          "primaryKey": false,
          "notNull": false
        },
        "occurred_at": {
          "name": "occurred_at",
          "type": "timestamp with time zone",
          "primaryKey": false,
          "notNull": true,
          "default": "now()"
        },
        "created_at": {
          "name": "created_at",
          "type": "timestamp with time zone",
          "primaryKey": false,
          "notNull": true,
          "default": "now()"
        },
        "updated_at": {
          "name": "updated_at",
          "type": "timestamp with time zone",
          "primaryKey": false,
          "notNull": true,
          "default": "now()"
        }
      },
      "indexes": {
        "inventory_transactions_org_id_idx": {
          "name": "inventory_transactions_org_id_idx",
          "columns": [
            {
              "expression": "org_id",
              "isExpression": false,
              "asc": true,
              "nulls": "last"
            }
          ],
          "isUnique": false,
          "concurrently": false,
          "method": "btree",
          "with": {}
        },
        "inventory_transactions_warehouse_id_idx": {
          "name": "inventory_transactions_warehouse_id_idx",
          "columns": [
            {
              "expression": "warehouse_id",
              "isExpression": false,
              "asc": true,
              "nulls": "last"
            }
          ],
          "isUnique": false,
          "concurrently": false,
          "method": "btree",
          "with": {}
        },
        "inventory_transactions_sku_id_idx": {
          "name": "inventory_transactions_sku_id_idx",
          "columns": [
            {
              "expression": "sku_id",
              "isExpression": false,
              "asc": true,
              "nulls": "last"
            }
          ],
          "isUnique": false,
          "concurrently": false,
          "method": "btree",
          "with": {}
        },
        "inventory_transactions_lot_id_idx": {
          "name": "inventory_transactions_lot_id_idx",
          "columns": [
            {
              "expression": "lot_id",
              "isExpression": false,
              "asc": true,
              "nulls": "last"
            }
          ],
          "isUnique": false,
          "concurrently": false,
          "method": "btree",
          "with": {}
        },
        "inventory_transactions_occurred_at_idx": {
          "name": "inventory_transactions_occurred_at_idx",
          "columns": [
            {
              "expression": "occurred_at",
              "isExpression": false,
              "asc": true,
              "nulls": "last"
            }
          ],
          "isUnique": false,
          "concurrently": false,
          "method": "btree",
          "with": {}
        }
      },
      "foreignKeys": {
        "inventory_transactions_warehouse_id_warehouses_id_fk": {
          "name": "inventory_transactions_warehouse_id_warehouses_id_fk",
          "tableFrom": "inventory_transactions",
          "tableTo": "warehouses",
          "columnsFrom": [
            "warehouse_id"
          ],
          "columnsTo": [
            "id"
          ],
          "onDelete": "restrict",
          "onUpdate": "no action"
        },
        "inventory_transactions_sku_id_product_skus_id_fk": {
          "name": "inventory_transactions_sku_id_product_skus_id_fk",
          "tableFrom": "inventory_transactions",
          "tableTo": "product_skus",
          "columnsFrom": [
            "sku_id"
          ],
          "columnsTo": [
            "id"
          ],
          "onDelete": "restrict",
          "onUpdate": "no action"
        },
        "inventory_transactions_lot_id_inventory_lots_id_fk": {
          "name": "inventory_transactions_lot_id_inventory_lots_id_fk",
          "tableFrom": "inventory_transactions",
          "tableTo": "inventory_lots",
          "columnsFrom": [
            "lot_id"
          ],
          "columnsTo": [
            "id"
          ],
          "onDelete": "set null",
          "onUpdate": "no action"
        },
        "inventory_transactions_from_location_id_locations_id_fk": {
          "name": "inventory_transactions_from_location_id_locations_id_fk",
          "tableFrom": "inventory_transactions",
          "tableTo": "locations",
          "columnsFrom": [
            "from_location_id"
          ],
          "columnsTo": [
            "id"
          ],
          "onDelete": "set null",
          "onUpdate": "no action"
        },
        "inventory_transactions_to_location_id_locations_id_fk": {
          "name": "inventory_transactions_to_location_id_locations_id_fk",
          "tableFrom": "inventory_transactions",
          "tableTo": "locations",
          "columnsFrom": [
            "to_location_id"
          ],
          "columnsTo": [
            "id"
          ],
          "onDelete": "set null",
          "onUpdate": "no action"
        },
        "inventory_transactions_performed_by_employees_id_fk": {
          "name": "inventory_transactions_performed_by_employees_id_fk",
          "tableFrom": "inventory_transactions",
          "tableTo": "employees",
          "columnsFrom": [
            "performed_by"
          ],
          "columnsTo": [
            "id"
          ],
          "onDelete": "set null",
          "onUpdate": "no action"
        }
      },
      "compositePrimaryKeys": {},
      "uniqueConstraints": {},
      "policies": {},
      "checkConstraints": {},
      "isRLSEnabled": false
    },
    "public.product_skus": {
      "name": "product_skus",
      "schema": "",
      "columns": {
        "id": {
          "name": "id",
          "type": "uuid",
          "primaryKey": true,
          "notNull": true,
          "default": "gen_random_uuid()"
        },
        "org_id": {
          "name": "org_id",
          "type": "text",
          "primaryKey": false,
          "notNull": true
        },
        "sku": {
          "name": "sku",
          "type": "text",
          "primaryKey": false,
          "notNull": true
        },
        "name": {
          "name": "name",
          "type": "text",
          "primaryKey": false,
          "notNull": true
        },
        "category": {
          "name": "category",
          "type": "text",
          "primaryKey": false,
          "notNull": false
        },
        "unit": {
          "name": "unit",
          "type": "text",
          "primaryKey": false,
          "notNull": true,
          "default": "'unit'"
        },
        "weight": {
          "name": "weight",
          "type": "double precision",
          "primaryKey": false,
          "notNull": false
        },
        "volume": {
          "name": "volume",
          "type": "double precision",
          "primaryKey": false,
          "notNull": false
        },
        "storage_class_label": {
          "name": "storage_class_label",
          "type": "text",
          "primaryKey": false,
          "notNull": true,
          "default": "'FIFO'"
        },
        "allocation_sort_field": {
          "name": "allocation_sort_field",
          "type": "lot_sort_field",
          "typeSchema": "public",
          "primaryKey": false,
          "notNull": true,
          "default": "'received_date'"
        },
        "allocation_sort_direction": {
          "name": "allocation_sort_direction",
          "type": "sort_direction",
          "typeSchema": "public",
          "primaryKey": false,
          "notNull": true,
          "default": "'asc'"
        },
        "created_at": {
          "name": "created_at",
          "type": "timestamp with time zone",
          "primaryKey": false,
          "notNull": true,
          "default": "now()"
        },
        "updated_at": {
          "name": "updated_at",
          "type": "timestamp with time zone",
          "primaryKey": false,
          "notNull": true,
          "default": "now()"
        }
      },
      "indexes": {
        "product_skus_org_id_idx": {
          "name": "product_skus_org_id_idx",
          "columns": [
            {
              "expression": "org_id",
              "isExpression": false,
              "asc": true,
              "nulls": "last"
            }
          ],
          "isUnique": false,
          "concurrently": false,
          "method": "btree",
          "with": {}
        },
        "product_skus_org_sku_idx": {
          "name": "product_skus_org_sku_idx",
          "columns": [
            {
              "expression": "org_id",
              "isExpression": false,
              "asc": true,
              "nulls": "last"
            },
            {
              "expression": "sku",
              "isExpression": false,
              "asc": true,
              "nulls": "last"
            }
          ],
          "isUnique": true,
          "concurrently": false,
          "method": "btree",
          "with": {}
        }
      },
      "foreignKeys": {},
      "compositePrimaryKeys": {},
      "uniqueConstraints": {},
      "policies": {},
      "checkConstraints": {},
      "isRLSEnabled": false
    },
    "public.delivery_orders": {
      "name": "delivery_orders",
      "schema": "",
      "columns": {
        "id": {
          "name": "id",
          "type": "uuid",
          "primaryKey": true,
          "notNull": true,
          "default": "gen_random_uuid()"
        },
        "org_id": {
          "name": "org_id",
          "type": "text",
          "primaryKey": false,
          "notNull": true
        },
        "warehouse_id": {
          "name": "warehouse_id",
          "type": "uuid",
          "primaryKey": false,
          "notNull": false
        },
        "destination": {
          "name": "destination",
          "type": "text",
          "primaryKey": false,
          "notNull": true
        },
        "destination_lat": {
          "name": "destination_lat",
          "type": "double precision",
          "primaryKey": false,
          "notNull": false
        },
        "destination_lng": {
          "name": "destination_lng",
          "type": "double precision",
          "primaryKey": false,
          "notNull": false
        },
        "required_skus": {
          "name": "required_skus",
          "type": "jsonb",
          "primaryKey": false,
          "notNull": true,
          "default": "'[]'::jsonb"
        },
        "preferred_date": {
          "name": "preferred_date",
          "type": "date",
          "primaryKey": false,
          "notNull": false
        },
        "status": {
          "name": "status",
          "type": "delivery_order_status",
          "typeSchema": "public",
          "primaryKey": false,
          "notNull": true,
          "default": "'pending'"
        },
        "notes": {
          "name": "notes",
          "type": "text",
          "primaryKey": false,
          "notNull": false
        },
        "created_at": {
          "name": "created_at",
          "type": "timestamp with time zone",
          "primaryKey": false,
          "notNull": true,
          "default": "now()"
        },
        "updated_at": {
          "name": "updated_at",
          "type": "timestamp with time zone",
          "primaryKey": false,
          "notNull": true,
          "default": "now()"
        }
      },
      "indexes": {
        "delivery_orders_org_id_idx": {
          "name": "delivery_orders_org_id_idx",
          "columns": [
            {
              "expression": "org_id",
              "isExpression": false,
              "asc": true,
              "nulls": "last"
            }
          ],
          "isUnique": false,
          "concurrently": false,
          "method": "btree",
          "with": {}
        },
        "delivery_orders_status_idx": {
          "name": "delivery_orders_status_idx",
          "columns": [
            {
              "expression": "status",
              "isExpression": false,
              "asc": true,
              "nulls": "last"
            }
          ],
          "isUnique": false,
          "concurrently": false,
          "method": "btree",
          "with": {}
        }
      },
      "foreignKeys": {
        "delivery_orders_warehouse_id_warehouses_id_fk": {
          "name": "delivery_orders_warehouse_id_warehouses_id_fk",
          "tableFrom": "delivery_orders",
          "tableTo": "warehouses",
          "columnsFrom": [
            "warehouse_id"
          ],
          "columnsTo": [
            "id"
          ],
          "onDelete": "set null",
          "onUpdate": "no action"
        }
      },
      "compositePrimaryKeys": {},
      "uniqueConstraints": {},
      "policies": {},
      "checkConstraints": {},
      "isRLSEnabled": false
    },
    "public.fuel_prices": {
      "name": "fuel_prices",
      "schema": "",
      "columns": {
        "id": {
          "name": "id",
          "type": "uuid",
          "primaryKey": true,
          "notNull": true,
          "default": "gen_random_uuid()"
        },
        "org_id": {
          "name": "org_id",
          "type": "text",
          "primaryKey": false,
          "notNull": false
        },
        "fuel_type": {
          "name": "fuel_type",
          "type": "fuel_type",
          "typeSchema": "public",
          "primaryKey": false,
          "notNull": true
        },
        "price_per_liter": {
          "name": "price_per_liter",
          "type": "numeric(10, 2)",
          "primaryKey": false,
          "notNull": true
        },
        "effective_date": {
          "name": "effective_date",
          "type": "date",
          "primaryKey": false,
          "notNull": true
        },
        "source": {
          "name": "source",
          "type": "text",
          "primaryKey": false,
          "notNull": false
        },
        "created_at": {
          "name": "created_at",
          "type": "timestamp with time zone",
          "primaryKey": false,
          "notNull": true,
          "default": "now()"
        },
        "updated_at": {
          "name": "updated_at",
          "type": "timestamp with time zone",
          "primaryKey": false,
          "notNull": true,
          "default": "now()"
        }
      },
      "indexes": {
        "fuel_prices_fuel_type_idx": {
          "name": "fuel_prices_fuel_type_idx",
          "columns": [
            {
              "expression": "fuel_type",
              "isExpression": false,
              "asc": true,
              "nulls": "last"
            }
          ],
          "isUnique": false,
          "concurrently": false,
          "method": "btree",
          "with": {}
        },
        "fuel_prices_effective_date_idx": {
          "name": "fuel_prices_effective_date_idx",
          "columns": [
            {
              "expression": "effective_date",
              "isExpression": false,
              "asc": true,
              "nulls": "last"
            }
          ],
          "isUnique": false,
          "concurrently": false,
          "method": "btree",
          "with": {}
        }
      },
      "foreignKeys": {},
      "compositePrimaryKeys": {},
      "uniqueConstraints": {},
      "policies": {},
      "checkConstraints": {},
      "isRLSEnabled": false
    },
    "public.shipment_plans": {
      "name": "shipment_plans",
      "schema": "",
      "columns": {
        "id": {
          "name": "id",
          "type": "uuid",
          "primaryKey": true,
          "notNull": true,
          "default": "gen_random_uuid()"
        },
        "org_id": {
          "name": "org_id",
          "type": "text",
          "primaryKey": false,
          "notNull": true
        },
        "order_id": {
          "name": "order_id",
          "type": "uuid",
          "primaryKey": false,
          "notNull": true
        },
        "vehicle_id": {
          "name": "vehicle_id",
          "type": "uuid",
          "primaryKey": false,
          "notNull": false
        },
        "route_warehouse_ids": {
          "name": "route_warehouse_ids",
          "type": "jsonb",
          "primaryKey": false,
          "notNull": true,
          "default": "'[]'::jsonb"
        },
        "total_distance_km": {
          "name": "total_distance_km",
          "type": "double precision",
          "primaryKey": false,
          "notNull": false
        },
        "estimated_hours": {
          "name": "estimated_hours",
          "type": "double precision",
          "primaryKey": false,
          "notNull": false
        },
        "fuel_cost_estimate": {
          "name": "fuel_cost_estimate",
          "type": "numeric(12, 2)",
          "primaryKey": false,
          "notNull": false
        },
        "created_at": {
          "name": "created_at",
          "type": "timestamp with time zone",
          "primaryKey": false,
          "notNull": true,
          "default": "now()"
        },
        "updated_at": {
          "name": "updated_at",
          "type": "timestamp with time zone",
          "primaryKey": false,
          "notNull": true,
          "default": "now()"
        }
      },
      "indexes": {
        "shipment_plans_org_id_idx": {
          "name": "shipment_plans_org_id_idx",
          "columns": [
            {
              "expression": "org_id",
              "isExpression": false,
              "asc": true,
              "nulls": "last"
            }
          ],
          "isUnique": false,
          "concurrently": false,
          "method": "btree",
          "with": {}
        },
        "shipment_plans_order_id_idx": {
          "name": "shipment_plans_order_id_idx",
          "columns": [
            {
              "expression": "order_id",
              "isExpression": false,
              "asc": true,
              "nulls": "last"
            }
          ],
          "isUnique": false,
          "concurrently": false,
          "method": "btree",
          "with": {}
        }
      },
      "foreignKeys": {
        "shipment_plans_order_id_delivery_orders_id_fk": {
          "name": "shipment_plans_order_id_delivery_orders_id_fk",
          "tableFrom": "shipment_plans",
          "tableTo": "delivery_orders",
          "columnsFrom": [
            "order_id"
          ],
          "columnsTo": [
            "id"
          ],
          "onDelete": "cascade",
          "onUpdate": "no action"
        },
        "shipment_plans_vehicle_id_vehicles_id_fk": {
          "name": "shipment_plans_vehicle_id_vehicles_id_fk",
          "tableFrom": "shipment_plans",
          "tableTo": "vehicles",
          "columnsFrom": [
            "vehicle_id"
          ],
          "columnsTo": [
            "id"
          ],
          "onDelete": "set null",
          "onUpdate": "no action"
        }
      },
      "compositePrimaryKeys": {},
      "uniqueConstraints": {},
      "policies": {},
      "checkConstraints": {},
      "isRLSEnabled": false
    },
    "public.vehicles": {
      "name": "vehicles",
      "schema": "",
      "columns": {
        "id": {
          "name": "id",
          "type": "uuid",
          "primaryKey": true,
          "notNull": true,
          "default": "gen_random_uuid()"
        },
        "org_id": {
          "name": "org_id",
          "type": "text",
          "primaryKey": false,
          "notNull": true
        },
        "plate_number": {
          "name": "plate_number",
          "type": "text",
          "primaryKey": false,
          "notNull": true
        },
        "type": {
          "name": "type",
          "type": "text",
          "primaryKey": false,
          "notNull": false
        },
        "capacity_weight": {
          "name": "capacity_weight",
          "type": "double precision",
          "primaryKey": false,
          "notNull": false
        },
        "capacity_volume": {
          "name": "capacity_volume",
          "type": "double precision",
          "primaryKey": false,
          "notNull": false
        },
        "home_warehouse_id": {
          "name": "home_warehouse_id",
          "type": "uuid",
          "primaryKey": false,
          "notNull": false
        },
        "created_at": {
          "name": "created_at",
          "type": "timestamp with time zone",
          "primaryKey": false,
          "notNull": true,
          "default": "now()"
        },
        "updated_at": {
          "name": "updated_at",
          "type": "timestamp with time zone",
          "primaryKey": false,
          "notNull": true,
          "default": "now()"
        }
      },
      "indexes": {
        "vehicles_org_id_idx": {
          "name": "vehicles_org_id_idx",
          "columns": [
            {
              "expression": "org_id",
              "isExpression": false,
              "asc": true,
              "nulls": "last"
            }
          ],
          "isUnique": false,
          "concurrently": false,
          "method": "btree",
          "with": {}
        },
        "vehicles_home_warehouse_id_idx": {
          "name": "vehicles_home_warehouse_id_idx",
          "columns": [
            {
              "expression": "home_warehouse_id",
              "isExpression": false,
              "asc": true,
              "nulls": "last"
            }
          ],
          "isUnique": false,
          "concurrently": false,
          "method": "btree",
          "with": {}
        }
      },
      "foreignKeys": {
        "vehicles_home_warehouse_id_warehouses_id_fk": {
          "name": "vehicles_home_warehouse_id_warehouses_id_fk",
          "tableFrom": "vehicles",
          "tableTo": "warehouses",
          "columnsFrom": [
            "home_warehouse_id"
          ],
          "columnsTo": [
            "id"
          ],
          "onDelete": "set null",
          "onUpdate": "no action"
        }
      },
      "compositePrimaryKeys": {},
      "uniqueConstraints": {},
      "policies": {},
      "checkConstraints": {},
      "isRLSEnabled": false
    },
    "public.notifications": {
      "name": "notifications",
      "schema": "",
      "columns": {
        "id": {
          "name": "id",
          "type": "uuid",
          "primaryKey": true,
          "notNull": true,
          "default": "gen_random_uuid()"
        },
        "org_id": {
          "name": "org_id",
          "type": "text",
          "primaryKey": false,
          "notNull": true
        },
        "warehouse_id": {
          "name": "warehouse_id",
          "type": "uuid",
          "primaryKey": false,
          "notNull": false
        },
        "target_user_id": {
          "name": "target_user_id",
          "type": "text",
          "primaryKey": false,
          "notNull": false
        },
        "source_type": {
          "name": "source_type",
          "type": "notification_source",
          "typeSchema": "public",
          "primaryKey": false,
          "notNull": true,
          "default": "'system'"
        },
        "title": {
          "name": "title",
          "type": "text",
          "primaryKey": false,
          "notNull": true
        },
        "body": {
          "name": "body",
          "type": "text",
          "primaryKey": false,
          "notNull": false
        },
        "read_at": {
          "name": "read_at",
          "type": "timestamp with time zone",
          "primaryKey": false,
          "notNull": false
        },
        "created_at": {
          "name": "created_at",
          "type": "timestamp with time zone",
          "primaryKey": false,
          "notNull": true,
          "default": "now()"
        },
        "updated_at": {
          "name": "updated_at",
          "type": "timestamp with time zone",
          "primaryKey": false,
          "notNull": true,
          "default": "now()"
        }
      },
      "indexes": {
        "notifications_org_id_idx": {
          "name": "notifications_org_id_idx",
          "columns": [
            {
              "expression": "org_id",
              "isExpression": false,
              "asc": true,
              "nulls": "last"
            }
          ],
          "isUnique": false,
          "concurrently": false,
          "method": "btree",
          "with": {}
        },
        "notifications_target_user_id_idx": {
          "name": "notifications_target_user_id_idx",
          "columns": [
            {
              "expression": "target_user_id",
              "isExpression": false,
              "asc": true,
              "nulls": "last"
            }
          ],
          "isUnique": false,
          "concurrently": false,
          "method": "btree",
          "with": {}
        },
        "notifications_warehouse_id_idx": {
          "name": "notifications_warehouse_id_idx",
          "columns": [
            {
              "expression": "warehouse_id",
              "isExpression": false,
              "asc": true,
              "nulls": "last"
            }
          ],
          "isUnique": false,
          "concurrently": false,
          "method": "btree",
          "with": {}
        }
      },
      "foreignKeys": {
        "notifications_warehouse_id_warehouses_id_fk": {
          "name": "notifications_warehouse_id_warehouses_id_fk",
          "tableFrom": "notifications",
          "tableTo": "warehouses",
          "columnsFrom": [
            "warehouse_id"
          ],
          "columnsTo": [
            "id"
          ],
          "onDelete": "cascade",
          "onUpdate": "no action"
        }
      },
      "compositePrimaryKeys": {},
      "uniqueConstraints": {},
      "policies": {},
      "checkConstraints": {},
      "isRLSEnabled": false
    }
  },
  "enums": {
    "public.dock_appointment_status": {
      "name": "dock_appointment_status",
      "schema": "public",
      "values": [
        "scheduled",
        "in_progress",
        "done",
        "cancelled"
      ]
    },
    "public.dock_direction": {
      "name": "dock_direction",
      "schema": "public",
      "values": [
        "inbound",
        "outbound",
        "both"
      ]
    },
    "public.location_type": {
      "name": "location_type",
      "schema": "public",
      "values": [
        "floor",
        "rack"
      ]
    },
    "public.employee_status": {
      "name": "employee_status",
      "schema": "public",
      "values": [
        "active",
        "terminated",
        "on_leave"
      ]
    },
    "public.staffing_plan_status": {
      "name": "staffing_plan_status",
      "schema": "public",
      "values": [
        "draft",
        "active"
      ]
    },
    "public.inventory_lot_status": {
      "name": "inventory_lot_status",
      "schema": "public",
      "values": [
        "available",
        "reserved",
        "depleted",
        "damaged"
      ]
    },
    "public.inventory_transaction_type": {
      "name": "inventory_transaction_type",
      "schema": "public",
      "values": [
        "inbound",
        "outbound",
        "transfer",
        "adjustment"
      ]
    },
    "public.lot_sort_field": {
      "name": "lot_sort_field",
      "schema": "public",
      "values": [
        "received_date",
        "expiry_date"
      ]
    },
    "public.sort_direction": {
      "name": "sort_direction",
      "schema": "public",
      "values": [
        "asc",
        "desc"
      ]
    },
    "public.delivery_order_status": {
      "name": "delivery_order_status",
      "schema": "public",
      "values": [
        "pending",
        "planned",
        "dispatched",
        "delivered",
        "cancelled"
      ]
    },
    "public.fuel_type": {
      "name": "fuel_type",
      "schema": "public",
      "values": [
        "ron95",
        "ron92",
        "diesel",
        "e5"
      ]
    },
    "public.notification_source": {
      "name": "notification_source",
      "schema": "public",
      "values": [
        "reslotting",
        "fuel_price",
        "staffing",
        "transportation",
        "system"
      ]
    }
  },
  "schemas": {},
  "sequences": {},
  "roles": {},
  "policies": {},
  "views": {},
  "_meta": {
    "columns": {},
    "schemas": {},
    "tables": {}
  }
}